adopt/__init__.py
adopt/__main__.py
adopt/azure_devops.py
adopt/config.py
adopt/exceptions.py
adopt/formatting.py
adopt/logging.py
adopt/work_items.py
adopt/backlog/__init__.py
adopt/backlog/check.py
adopt/backlog/fix.py
adopt/backlog/sort.py
adopt/cli/__init__.py
adopt/cli/options.py
adopt/cli/backlog/__init__.py
adopt/cli/backlog/check.py
adopt/cli/backlog/fix.py
adopt/cli/backlog/options.py
adopt/cli/backlog/print.py
adopt/cli/backlog/sort.py
adopt-0.5.3.dist-info/licenses/LICENSE
adopt-0.5.3.dist-info/METADATA
adopt-0.5.3.dist-info/WHEEL
adopt-0.5.3.dist-info/entry_points.txt
adopt-0.5.3.dist-info/top_level.txt
adopt-0.5.3.dist-info/RECORD
