Metadata-Version: 2.4
Name: adopt
Version: 0.5.3
Summary: Set of pragmatic tools to automate working with Azure Devops
Author-email: Christophe Van Dijck <christophe.vdijck@gmail.com>
License: BSD-3-Clause
Project-URL: Homepage, https://github.com/cvandijck/azure-devops-tools
Project-URL: Repository, https://github.com/cvandijck/azure-devops-tools
Classifier: Development Status :: 3 - Alpha
Classifier: Intended Audience :: Developers
Classifier: Programming Language :: Python :: 3
Requires-Python: >=3.9
License-File: LICENSE
Requires-Dist: azure-devops
Requires-Dist: python-dotenv
Requires-Dist: click
Requires-Dist: prettytable
Requires-Dist: toml
Requires-Dist: contexttimer
Dynamic: license-file
